dataheroes/__init__.py
dataheroes/cli.py
dataheroes/common.py
dataheroes/configuration.py
dataheroes/utils.py
dataheroes/version.py
dataheroes/version_type.py
dataheroes/version_type_no_internet.py
dataheroes/core/__init__.py
dataheroes/core/common.py
dataheroes/core/helpers.py
dataheroes/core/numpy_extra.py
dataheroes/core/types.py
dataheroes/core/coreset/__init__.py
dataheroes/core/coreset/_base.py
dataheroes/core/coreset/common.py
dataheroes/core/coreset/coreset_analytics.py
dataheroes/core/coreset/coreset_dtc.py
dataheroes/core/coreset/coreset_dtr.py
dataheroes/core/coreset/coreset_gmm.py
dataheroes/core/coreset/coreset_kmeans.py
dataheroes/core/coreset/coreset_lg.py
dataheroes/core/coreset/coreset_nmf.py
dataheroes/core/coreset/coreset_pca.py
dataheroes/core/coreset/coreset_qda.py
dataheroes/core/coreset/coreset_reg.py
dataheroes/core/coreset/coreset_svd.py
dataheroes/core/coreset/coreset_svm.py
dataheroes/core/coreset/coreset_uniform.py
dataheroes/core/coreset/exceptions.py
dataheroes/core/estimator/__init__.py
dataheroes/core/estimator/_base.py
dataheroes/core/estimator/lightweight.py
dataheroes/core/estimator/unified.py
dataheroes/core/estimator/uniform.py
dataheroes/core/sklearn_extra/__init__.py
dataheroes/core/sklearn_extra/_target_encoder.py
dataheroes/core/sklearn_extra/array_encoder.py
dataheroes/core/sklearn_extra/column_transformer.py
dataheroes/core/sklearn_extra/preprocessing.py
dataheroes/core/sklearn_extra/validation.py
dataheroes/core/sklearn_extra/wgmm.py
dataheroes/core/sklearn_extra/whist.py
dataheroes/core/sklearn_extra/wkmeans_plusplus.py
dataheroes/core/sklearn_extra/wpca.py
dataheroes/core/sklearn_extra/wqda.py
dataheroes/core/sklearn_extra/wsvd.py
dataheroes/core/sklearn_extra/sklearn_1_5_1_mask/__init__.py
dataheroes/core/sklearn_extra/sklearn_1_5_1_mask/_config.py
dataheroes/core/sklearn_extra/sklearn_1_5_1_mask/base.py
dataheroes/core/sklearn_extra/sklearn_1_5_1_mask/exceptions.py
dh_pyspark-0.4.6.dist-info/METADATA
dh_pyspark-0.4.6.dist-info/WHEEL
dh_pyspark-0.4.6.dist-info/top_level.txt
dh_pyspark-0.4.6.dist-info/RECORD
